eaglewrapper/__init__.py
eaglewrapper/eagle.py
EagleWrapper-1.1.1.dist-info/LICENSE
EagleWrapper-1.1.1.dist-info/METADATA
EagleWrapper-1.1.1.dist-info/WHEEL
EagleWrapper-1.1.1.dist-info/top_level.txt
EagleWrapper-1.1.1.dist-info/RECORD
