Metadata-Version: 2.1
Name: EagleWrapper
Version: 1.1.1
Summary: A wrapper for an image management tool named Eagle.
Home-page: https://github.com/NatLee/eagle-wrapper
Author: Nat Lee
Author-email: natlee.work@gmail.com
Project-URL: Documentation, https://github.com/NatLee/eagle-wrapper
Project-URL: Bug Reports, https://github.com/NatLee/eagle-wrapper/issues
Project-URL: Source Code, https://github.com/NatLee/eagle-wrapper
Project-URL: Official API Documentation, https://api.eagle.cool/
Keywords: eagle,image management,wrapper
Classifier: Development Status :: 5 - Production/Stable
Classifier: Intended Audience :: Developers
Classifier: Topic :: Software Development :: Build Tools
Classifier: Programming Language :: Python :: 3
Classifier: Programming Language :: Python :: 3.6
Classifier: Programming Language :: Python :: 3.7
Classifier: Programming Language :: Python :: 3.8
Classifier: Programming Language :: Python :: 3.9
Classifier: Programming Language :: Python :: 3.10
Classifier: Programming Language :: Python :: 3.11
Classifier: Programming Language :: Python :: 3 :: Only
Classifier: License :: OSI Approved :: MIT License
Classifier: Operating System :: OS Independent
Requires-Python: >=3.6
License-File: LICENSE
Requires-Dist: requests
Requires-Dist: loguru
Provides-Extra: dev
Requires-Dist: check-manifest ; extra == 'dev'
